datar_arrow/__init__.py
datar_arrow/api/__init__.py
datar_arrow/api/arithm.py
datar_arrow/api/asis.py
datar_arrow/api/bessel.py
datar_arrow/api/constants.py
datar_arrow/api/cum.py
datar_arrow/api/date.py
datar_arrow/api/factor.py
datar_arrow/api/random.py
datar_arrow/api/seq.py
datar_arrow/api/sets.py
datar_arrow/api/special.py
datar_arrow/api/string.py
datar_arrow/api/trig.py
datar_arrow/api/which.py
datar_arrow/arrow_ext.py
datar_arrow/plugin.py
datar_arrow/utils.py
datar_arrow/version.py
datar_arrow-0.1.1.dist-info/LICENSE
datar_arrow-0.1.1.dist-info/METADATA
datar_arrow-0.1.1.dist-info/WHEEL
datar_arrow-0.1.1.dist-info/entry_points.txt
datar_arrow-0.1.1.dist-info/RECORD
