Metadata-Version: 2.1
Name: datar-arrow
Version: 0.1.1
Summary: The pyarrow backend for datar
License: MIT
Author: pwwang
Author-email: pwwang@pwwang.com
Requires-Python: >=3.8,<4.0
Classifier: License :: OSI Approved :: MIT License
Classifier: Programming Language :: Python :: 3
Classifier: Programming Language :: Python :: 3.8
Classifier: Programming Language :: Python :: 3.9
Classifier: Programming Language :: Python :: 3.10
Classifier: Programming Language :: Python :: 3.11
Provides-Extra: all
Requires-Dist: datar (>=0.15,<0.16)
Requires-Dist: pyarrow (>=13,<14)
Requires-Dist: scipy (>=1.6,<2.0) ; extra == "all"
Requires-Dist: wcwidth (>=0.2,<0.3) ; extra == "all"
